cresto/__init__.py
cresto-0.0.1.dist-info/LICENSE.txt
cresto-0.0.1.dist-info/METADATA
cresto-0.0.1.dist-info/WHEEL
cresto-0.0.1.dist-info/top_level.txt
cresto-0.0.1.dist-info/RECORD
